README.txt
setup.py
collective/__init__.py
collective.js.slimbox2.egg-info/PKG-INFO
collective.js.slimbox2.egg-info/SOURCES.txt
collective.js.slimbox2.egg-info/dependency_links.txt
collective.js.slimbox2.egg-info/entry_points.txt
collective.js.slimbox2.egg-info/namespace_packages.txt
collective.js.slimbox2.egg-info/not-zip-safe
collective.js.slimbox2.egg-info/requires.txt
collective.js.slimbox2.egg-info/top_level.txt
collective/js/__init__.py
collective/js/slimbox2/__init__.py
collective/js/slimbox2/configure.zcml
collective/js/slimbox2/browser/__init__.py
collective/js/slimbox2/browser/common.py
collective/js/slimbox2/browser/configure.zcml
collective/js/slimbox2/browser/slimbox2-overrides.css
collective/js/slimbox2/browser/resources/README.txt
collective/js/slimbox2/browser/resources/example.html
collective/js/slimbox2/browser/resources/example.jpg
collective/js/slimbox2/browser/resources/css/closelabel.gif
collective/js/slimbox2/browser/resources/css/loading.gif
collective/js/slimbox2/browser/resources/css/nextlabel.gif
collective/js/slimbox2/browser/resources/css/prevlabel.gif
collective/js/slimbox2/browser/resources/css/slimbox2-rtl.css
collective/js/slimbox2/browser/resources/css/slimbox2.css
collective/js/slimbox2/browser/resources/extra/android-market.js
collective/js/slimbox2/browser/resources/extra/autoactivation.js
collective/js/slimbox2/browser/resources/extra/fix-urls.js
collective/js/slimbox2/browser/resources/extra/flickr.js
collective/js/slimbox2/browser/resources/extra/picasaweb.js
collective/js/slimbox2/browser/resources/js/slimbox2.js
collective/js/slimbox2/browser/resources/src/autoload.js
collective/js/slimbox2/browser/resources/src/slimbox2.js
collective/js/slimbox2/profiles/default/browserlayer.xml
collective/js/slimbox2/profiles/default/cssregistry.xml
collective/js/slimbox2/profiles/default/jsregistry.xml
collective/js/slimbox2/profiles/default/metadata.xml
docs/HISTORY.txt