Metadata-Version: 1.0
Name: collective.js.slimbox2
Version: 1.4
Summary: Slimbox is a 4 KB visual clone of the popular Lightbox 2 script by Lokesh Dhakar, written using the jQuery javascript library.
Home-page: http://svn.plone.org/svn/collective/collective.js.slimbox2
Author: JeanMichel FRANCOIS aka toutpt
Author-email: jeanmichel.francois@makina-corpus.com
License: GPL
Platform: UNKNOWN
Classifier: Programming Language :: Python
